qr_vec/__init__.py
qr_vec/qrvector.py
QR_Vec-0.0.1.dist-info/LICENSE
QR_Vec-0.0.1.dist-info/METADATA
QR_Vec-0.0.1.dist-info/WHEEL
QR_Vec-0.0.1.dist-info/top_level.txt
QR_Vec-0.0.1.dist-info/RECORD
